dev_pipeline_core-0.4.0.dist-info/DESCRIPTION.rst
dev_pipeline_core-0.4.0.dist-info/METADATA
dev_pipeline_core-0.4.0.dist-info/RECORD
dev_pipeline_core-0.4.0.dist-info/WHEEL
dev_pipeline_core-0.4.0.dist-info/entry_points.txt
dev_pipeline_core-0.4.0.dist-info/metadata.json
dev_pipeline_core-0.4.0.dist-info/top_level.txt
devpipeline_core/__init__.py
devpipeline_core/command.py
devpipeline_core/configinfo.py
devpipeline_core/env.py
devpipeline_core/executor.py
devpipeline_core/paths.py
devpipeline_core/plugin.py
devpipeline_core/resolve.py
devpipeline_core/sanitizer.py
devpipeline_core/toolsupport.py
devpipeline_core/version.py
