Metadata-Version: 2.0
Name: dev-pipeline-core
Version: 0.4.0
Summary: Core libraries for dev-pipeline
Home-page: https://github.com/dev-pipeline/dev-pipeline-core
Author: Stephen Newell
Author-email: UNKNOWN
License: BSD-2
Platform: UNKNOWN
Classifier: Development Status :: 2 - Pre-Alpha
Classifier: Intended Audience :: Developers
Classifier: License :: OSI Approved :: BSD License
Classifier: Topic :: Software Development
Classifier: Topic :: Utilities
